{"DocumentConnection":{"type":"DocumentConnection","resolveType":"multiCollectionDocumentList","collections":["listings"]},"Node":{"type":"Node","resolveType":"nodeDocument"},"DocumentNode":{"type":"DocumentNode","resolveType":"multiCollectionDocument","createDocument":"create","updateDocument":"update"},"Listings":{"type":"Listings","resolveType":"collectionDocument","collection":"listings","createListings":"create","updateListings":"update"},"ListingsConnection":{"type":"ListingsConnection","resolveType":"collectionDocumentList","collection":"listings"}}